lazyimp/__init__.py
lazyimp/_capture.c
lazyimp/_capture.cpython-312-darwin.so
lazyimp/capture.py
lazyimp/lazyglobals.py
lazyimp/proxy.py
lazyimp-0.0.6.dist-info/licenses/LICENSE
lazyimp-0.0.6.dist-info/METADATA
lazyimp-0.0.6.dist-info/WHEEL
lazyimp-0.0.6.dist-info/top_level.txt
lazyimp-0.0.6.dist-info/RECORD
